greenformer/__init__.py
greenformer/auto_fact.py
greenformer/lr_module.py
greenformer/version.py
PyAutoFact-0.2.2.dist-info/LICENSE
PyAutoFact-0.2.2.dist-info/METADATA
PyAutoFact-0.2.2.dist-info/WHEEL
PyAutoFact-0.2.2.dist-info/top_level.txt
PyAutoFact-0.2.2.dist-info/RECORD
