Metadata-Version: 2.1
Name: PyAutoFact
Version: 0.2.2
Summary: Automatic Factorization package for PyTorch modules
Home-page: https://github.com/SamuelCahyawijaya/greenformer
Author: Samuel Cahyawijaya
Author-email: samuel.cahyawijaya@gmail.com
License: UNKNOWN
Project-URL: Bug Tracker, https://github.com/SamuelCahyawijaya/greenformer/issues
Platform: UNKNOWN
Classifier: Programming Language :: Python :: 3
Classifier: License :: OSI Approved :: MIT License
Classifier: Operating System :: OS Independent
Requires-Python: >=3.3
License-File: LICENSE
Requires-Dist: matrix-fact (==1.1.2)
Requires-Dist: transformers (==4.8.2)
Requires-Dist: torch (>=1.5.0)
Requires-Dist: scipy
Requires-Dist: cvxopt (==1.2.6)
Requires-Dist: matplotlib (==3.4.2)
Requires-Dist: seaborn (==0.11.1)
Requires-Dist: sklearn
